AUTHORS.rst
LICENSE.txt
MANIFEST.in
README.rst
setup.py
cgenerator/__init__.py
cgenerator/cgenerator.py
cgenerator.egg-info/PKG-INFO
cgenerator.egg-info/SOURCES.txt
cgenerator.egg-info/dependency_links.txt
cgenerator.egg-info/entry_points.txt
cgenerator.egg-info/not-zip-safe
cgenerator.egg-info/requires.txt
cgenerator.egg-info/top_level.txt
cgenerator/templates/clist.c.tmp
cgenerator/templates/clist.h.tmp
cgenerator/templates/ctypes.h.tmp
cgenerator/templates/cvector.c.tmp
cgenerator/templates/cvector.h.tmp
cgenerator/templates/entity.c.tmp
cgenerator/templates/entity.h.tmp
tests/__init__.py
tests/test_main.py