Metadata-Version: 1.0
Name: cgenerator
Version: 0.1.4
Summary: Tools C container generator
Home-page: https://github.com/alexeyvoronin777/cgenerator
Author: Alexey Voronin
Author-email: alexeyvoronin777@gmail.com
License:                     GNU GENERAL PUBLIC LICENSE